pyosmanager/__init__.py
pyosmanager/pyosmanager.py
pyosmanager/responses.py
pyosmanager-0.2.3.dist-info/LICENSE
pyosmanager-0.2.3.dist-info/METADATA
pyosmanager-0.2.3.dist-info/WHEEL
pyosmanager-0.2.3.dist-info/top_level.txt
pyosmanager-0.2.3.dist-info/RECORD
