Metadata-Version: 2.1
Name: pyosmanager
Version: 0.2.3
Summary: Python client for Open Surplus Manager
Home-page: https://github.com/JoseRMorales/pyOSManager/
Author: Jose R. Morales
Author-email: dev@josermorales.com
License: MIT
Keywords: API,Open Surplus Manager,API client,API wrapper,async,iot
Classifier: Development Status :: 4 - Beta
Classifier: Intended Audience :: Developers
Classifier: Topic :: Software Development :: Build Tools
Classifier: License :: OSI Approved :: MIT License
Classifier: Programming Language :: Python :: 3
Classifier: Programming Language :: Python :: 3.12
License-File: LICENSE
Requires-Dist: aiohttp
Requires-Dist: backoff
